{
  "id": "week-2026-04-13",
  "generated_at": "2026-04-12T16:18:46.589Z",
  "timezone": "America/Los_Angeles",
  "items": [
    {
      "id": "f8d38de4d318",
      "scheduled_date": "2026-04-13",
      "scheduled_time": "05:30",
      "scheduled_at": "2026-04-13T12:30:00.000Z",
      "timezone": "America/Los_Angeles",
      "weekday": "monday",
      "slot_type": "baseline",
      "status": "planned",
      "content_type": "decoder_ring",
      "pillar": "Decoder Ring",
      "topic_thesis": "To found trust without building a cult, leaders must transgress, recognize, release, and submit.",
      "angle": "Do not summarize the news; diagnose the pattern underneath it.",
      "hook": "Most people are misreading what this story is actually about. to found trust without building a cult, leaders must transgress, recognize, release, and submit.",
      "source_bundle_id": null,
      "timely_subject": null,
      "draft_ref": null,
      "winner_id": null,
      "risk_level": "low",
      "freshness_deadline": null,
      "publish_payload": null
    },
    {
      "id": "3134f844e313",
      "scheduled_date": "2026-04-14",
      "scheduled_time": "05:30",
      "scheduled_at": "2026-04-14T12:30:00.000Z",
      "timezone": "America/Los_Angeles",
      "weekday": "tuesday",
      "slot_type": "baseline",
      "status": "planned",
      "content_type": "from_the_mailbag",
      "pillar": "From the Mailbag",
      "topic_thesis": "Living law has to submit itself to the same anti-scapegoat logic it imposes on everyone else.",
      "angle": "The interpretation is the point, not the quote itself.",
      "hook": "A note landed in my inbox that names a pattern I keep seeing. living law has to submit itself to the same anti-scapegoat logic it imposes on everyone else.",
      "source_bundle_id": null,
      "timely_subject": null,
      "draft_ref": null,
      "winner_id": null,
      "risk_level": "low",
      "freshness_deadline": null,
      "publish_payload": null
    },
    {
      "id": "d710af245935",
      "scheduled_date": "2026-04-15",
      "scheduled_time": "05:30",
      "scheduled_at": "2026-04-15T12:30:00.000Z",
      "timezone": "America/Los_Angeles",
      "weekday": "wednesday",
      "slot_type": "baseline",
      "status": "planned",
      "content_type": "extracted_insight",
      "pillar": "Extracted Insights",
      "topic_thesis": "The faster knowledge changes, the more an organization needs a stable myth layer.",
      "angle": "Name the concept, explain it plainly, and show why it matters now.",
      "hook": "The mistake leaders keep making is thinking the faster knowledge changes, the more an organization needs a stable myth layer.",
      "source_bundle_id": null,
      "timely_subject": null,
      "draft_ref": null,
      "winner_id": null,
      "risk_level": "low",
      "freshness_deadline": null,
      "publish_payload": null
    },
    {
      "id": "45ccda3ae614",
      "scheduled_date": "2026-04-16",
      "scheduled_time": "05:30",
      "scheduled_at": "2026-04-16T12:30:00.000Z",
      "timezone": "America/Los_Angeles",
      "weekday": "thursday",
      "slot_type": "baseline",
      "status": "planned",
      "content_type": "archetype_diagnosis",
      "pillar": "Archetype Diagnosis",
      "topic_thesis": "Apollo and Dionysus are complements, not substitutes: one optimizes the known system, the other governs death and rebirth.",
      "angle": "Make the pattern recognizable fast and show what drives it.",
      "hook": "You can tell a team is drifting into theater when apollo and dionysus are complements, not substitutes: one optimizes the known system, the other governs death and rebirth.",
      "source_bundle_id": null,
      "timely_subject": null,
      "draft_ref": null,
      "winner_id": null,
      "risk_level": "low",
      "freshness_deadline": null,
      "publish_payload": null
    },
    {
      "id": "016576d74be9",
      "scheduled_date": "2026-04-17",
      "scheduled_time": "05:30",
      "scheduled_at": "2026-04-17T12:30:00.000Z",
      "timezone": "America/Los_Angeles",
      "weekday": "friday",
      "slot_type": "baseline",
      "status": "planned",
      "content_type": "ritual_recipe",
      "pillar": "Ritual Recipes",
      "topic_thesis": "The Weekly Crossing is a practical recurring ritual for metabolizing drift before it hardens.",
      "angle": "Start with a recurring problem and end with a usable move.",
      "hook": "If your team keeps repeating the same failure, stop adding process. the weekly crossing is a practical recurring ritual for metabolizing drift before it hardens.",
      "source_bundle_id": null,
      "timely_subject": null,
      "draft_ref": null,
      "winner_id": null,
      "risk_level": "low",
      "freshness_deadline": null,
      "publish_payload": null
    }
  ]
}
